{
	"pages": [ //pages数组中第一项表示应用启动页，参考：https://uniapp.dcloud.io/collocation/pages

		{
			"path": "pages/index/index",
			"style": {
				// "navigationBarTitleText": "首页",
				// "navigationBarBackgroundColor": "#E5EDF9",
				// "navigationBarTextStyle": "black"
				"navigationStyle": "custom",
				"onReachBottomDistance": 50
			}
		},
		
		{
			"path": "pages/login/login",
			"style": {
				// "navigationBarTitleText": "登录",
				// "navigationBarBackgroundColor": "#fff",
				// "navigationBarTextStyle": "black",
				"navigationStyle": "custom"
			}

		},
		{
			"path": "pages/user/user",
			"style": {
				// "navigationBarTitleText": "个人信息",
				// "navigationBarBackgroundColor": "#fff",
				// "navigationBarTextStyle": "black"
				"navigationStyle": "custom"
			}
		
		},
		
		{
			"path": "pages/agree/agree",
			"style": {
				// "navigationBarTitleText": "",
				// "enablePullDownRefresh": false
				"navigationStyle": "custom"
			}

		},
		{
			"path": "pages/user/set/set",
			"style": {
				"navigationBarTitleText": "设置",
				"enablePullDownRefresh": false
			}
		
		},
		{
			"path": "pages/user/info/info",
			"style": {
				"navigationBarTitleText": "个人信息",
				"navigationBarBackgroundColor": "#fff",
				"navigationBarTextStyle": "black"
			}

		}
	],
	"subPackages": [{
			"root": "childPage",
			"pages": [
				
				{
					"path": "answer/answer",
					"style": {
						// "navigationBarTitleText": "问题反馈",
						// "navigationBarBackgroundColor": "#fff",
						// "navigationBarTextStyle": "black",
						"navigationStyle": "custom"
					}
				}
			]
		},
		{
			"root": "childCont",
			"pages": [
				{
					"path": "figure/figure_video",
					"style": {
						// "navigationBarTitleText": "定制数字人形象",
						// "navigationBarBackgroundColor": "#fff",
						// "navigationBarTextStyle": "black"
						"navigationStyle": "custom"
					}

				},
				{
					"path": "figure/figure_file",
					"style": {
						"navigationBarTitleText": "定制信息审核",
						"navigationBarBackgroundColor": "#fff",
						"navigationBarTextStyle": "black"
						// "navigationStyle": "custom"
					}

				},
				{
					"path": "figure/figure_voice",
					"style": {
						// "navigationBarTitleText": "定制数字人形象",
						// "navigationBarBackgroundColor": "#fff",
						// "navigationBarTextStyle": "black"
						"navigationStyle": "custom"
					}

				},
				{
					"path": "figure/figure_oral",
					"style": {
						// "navigationBarTitleText": "定制数字人形象",
						// "navigationBarBackgroundColor": "#fff",
						// "navigationBarTextStyle": "black"
						"navigationStyle": "custom"
					}

				},
				{
					"path": "figure/my_video",
					"style": {
						// "navigationBarTitleText": "我的视频",
						// "navigationBarBackgroundColor": "#fff",
						// "navigationBarTextStyle": "black"
						"navigationStyle": "custom"
					}

				},
				{
					"path": "figure/pay_success",
					"style": {
						// "navigationBarTitleText": "我的视频",
						// "navigationBarBackgroundColor": "#fff",
						// "navigationBarTextStyle": "black"
						"navigationStyle": "custom"
					}

				},
				{
					"path": "figure/pay_video",
					"style": {
						// "navigationBarTitleText": "我的视频",
						// "navigationBarBackgroundColor": "#fff",
						// "navigationBarTextStyle": "black"
						"navigationStyle": "custom"
					}

				},
				{
					"path": "figure/play",
					"style": {
						// "navigationBarTitleText": "我的视频",
						// "navigationBarBackgroundColor": "#fff",
						// "navigationBarTextStyle": "black"
						"navigationStyle": "custom"
					}

				},
				{
					"path": "figure/figure_product",
					"style": {
						// "navigationBarTitleText": "定制列表",
						// "navigationBarBackgroundColor": "#fff",
						// "navigationBarTextStyle": "black"
						"navigationStyle": "custom"
					}

				},
				{
					"path": "figure/my_voice",
					"style": {
						"navigationBarTitleText": "定制列表",
						"navigationBarBackgroundColor": "#fff",
						"navigationBarTextStyle": "black"
					}

				},
				{
					"path": "figure/video_detail",
					"style": {
						"navigationBarTitleText": "定制详情",
						"navigationBarBackgroundColor": "#fff",
						"navigationBarTextStyle": "black"
					}

				},
				{
					"path": "figure/voice_list",
					"style": {
						// "navigationBarTitleText": "素材预览",
						// "navigationBarBackgroundColor": "#fff",
						// "navigationBarTextStyle": "black"
						"navigationStyle": "custom"
					}

				},
				{
					"path": "figure/pay_voice",
					"style": {
						// "navigationBarTitleText": "素材预览",
						// "navigationBarBackgroundColor": "#fff",
						// "navigationBarTextStyle": "black"
						"navigationStyle": "custom"
					}

				},
				{
					"path": "figure/compose_voice",
					"style": {
						// "navigationBarTitleText": "素材预览",
						// "navigationBarBackgroundColor": "#fff",
						// "navigationBarTextStyle": "black"
						"navigationStyle": "custom"
					}

				},
				{
					"path": "figure/compose_list",
					"style": {
						// "navigationBarTitleText": "素材预览",
						// "navigationBarBackgroundColor": "#fff",
						// "navigationBarTextStyle": "black"
						"navigationStyle": "custom"
					}

				},

				{
					"path": "figure/figure_order",
					"style": {
						// "navigationBarTitleText": "素材预览",
						// "navigationBarBackgroundColor": "#fff",
						// "navigationBarTextStyle": "black"
						"navigationStyle": "custom"
					}

				},

				{
					"path": "figure/figure_order_detail",
					"style": {
						// "navigationBarTitleText": "素材预览",
						// "navigationBarBackgroundColor": "#fff",
						// "navigationBarTextStyle": "black"
						"navigationStyle": "custom"
					}

				},
				
	            {
					"path": "figure/clone_require",
					"style": {
						"navigationBarTitleText": "形象克隆要求",
						"enablePullDownRefresh": false
					}
				},

				{
					"path" : "realName/realName",
					"style" : 
					{
						// "navigationBarTitleText" : "实名认证",
						// "enablePullDownRefresh" : false,
						"navigationStyle": "custom"
					}
				},
				{
					"path" : "realName/backMini",
					"style" : 
					{
						// "navigationBarTitleText" : "返回小程序",
						// "enablePullDownRefresh" : false,
						"navigationStyle": "custom"
					}
				},
				
				{
					"path" : "clone/voice_clone",
					"style" : 
					{
						"navigationBarTitleText" : "声音克隆",
						"enablePullDownRefresh" : false,
						"navigationBarBackgroundColor": "#fff",
						"navigationBarTextStyle": "black"
					}
				},
				
				{
					"path" : "clone/copy_voice",
					"style" : 
					{
						"navigationBarTitleText" : "声音合成",
						"enablePullDownRefresh" : false,
						"navigationBarBackgroundColor": "#fff",
						"navigationBarTextStyle": "black"
					}
				},
				
				{
					"path" : "clone/my_voice",
					"style" : 
					{
						"navigationBarTitleText" : "我的声音",
						"enablePullDownRefresh" : false,
						"navigationBarBackgroundColor": "#fff",
						"navigationBarTextStyle": "black"
					}
				},
				
				{
					"path" : "clone/voice_order",
					"style" : 
					{
						"navigationBarTitleText" : "订单记录",
						"enablePullDownRefresh" : false,
						"navigationBarBackgroundColor": "#fff",
						"navigationBarTextStyle": "black"
					}
				},
				
				{
					"path" : "clone/clone_history",
					"style" : 
					{
						"navigationBarTitleText" : "历史记录",
						"enablePullDownRefresh" : false,
						"navigationBarBackgroundColor": "#fff",
						"navigationBarTextStyle": "black"
					}
				},
				
				{
					"path" : "clone/clone_qs",
					"style" : 
					{
						"navigationBarTitleText" : "录音规范",
						"enablePullDownRefresh" : false,
						"navigationBarBackgroundColor": "#fff",
						"navigationBarTextStyle": "black"
					}
				},
				{
					"path" : "clone/pay_clone",
					"style" : 
					{
						"navigationBarTitleText" : "声音克隆",
						"enablePullDownRefresh" : false
					}
				}
			]
		}
	],

	"globalStyle": {
		"navigationBarTextStyle": "black",
		"navigationBarTitleText": "无忧秘书AI",
		"navigationBarBackgroundColor": "#F6F8Fb",
		"backgroundColor": "#F6F8Fb"
	},
	"tabBar": {
		"color": "#131D34",
		"selectedColor": "#1F64FF",
		"backgroundColor": "#fff",
		"borderStyle": "black",
		"list": [{
				"pagePath": "pages/index/index",
				"text": "数字人",
				"iconPath": "static/nav/shouye1.png",
				"selectedIconPath": "static/nav/shouye.png"
			},
			// {
			// 	"pagePath": "pages/apply/apply",
			// 	"text": "助理",
			// 	"iconPath": "static/nav/yingyong1.png",
			// 	"selectedIconPath": "static/nav/yingyong.png"
			// },
			{
				"pagePath": "pages/user/user",
				"text": "我的",
				"iconPath": "static/nav/user1.png",
				"selectedIconPath": "static/nav/user.png"
			}
		]
	},
	"uniIdRouter": {}
}